{
	"instance" : {
		"resetPosition" : "Alvaro 4/1/2018 17:50",
		"checkEnfGame" : "apiorno 6/10/2018 15:33",
		"initializeSprite" : "Alvaro 10/30/2017 21:13",
		"updateCollisionShapeUsing:" : "Alvaro 10/28/2017 18:06",
		"negateY" : "Alvaro 11/1/2017 14:59",
		"initialize" : "Alvaro 11/1/2017 14:59",
		"negateX" : "Alvaro 10/28/2017 13:52",
		"checkCollisions" : "apiorno 6/10/2018 15:33",
		"initializeCollisionShape" : "Alvaro 11/1/2017 14:58",
		"initializeOn:" : "Alvaro 10/27/2017 22:52",
		"playCollisionSound" : "Alvaro 10/28/2017 13:31"
	},
	"class" : {
		"on:" : "Alvaro 10/27/2017 22:51"
	}
}